MANIFEST.in
README.md
dev-requirements.txt
requirements.txt
setup.py
djinja/__init__.py
djinja/cli.py
djinja/conftree.py
djinja/main.py
djinja/contrib/__init__.py
djinja/contrib/basic.py
djinja/contrib/file.py
docker_jinja.egg-info/PKG-INFO
docker_jinja.egg-info/SOURCES.txt
docker_jinja.egg-info/dependency_links.txt
docker_jinja.egg-info/requires.txt
docker_jinja.egg-info/top_level.txt
scripts/dj
test/test_cli.py
test/test_conftree.py
test/test_contrib.py
test/test_core.py