Metadata-Version: 1.1
Name: docker-jinja
Version: 1.0.0
Summary: Extend your dockerfiles with Jinja2 syntax to to more awesome dockerfiles
Home-page: https://github.com/Grokzen/docker-jinja
Author: Johan Andersson
Author-email: Grokzen@gmail.com
License: MIT
Platform: UNKNOWN
Classifier: Development Status :: 3 - Alpha
Classifier: Programming Language :: Python
Classifier: Programming Language :: Python :: 2.7
Classifier: Programming Language :: Python :: 3.3
Classifier: Programming Language :: Python :: 3.4
Classifier: Environment :: Console
Classifier: Operating System :: POSIX
